{"__type__":"cc.TiledMapAsset","_name":"map2","tmxXmlStr":"<?xml version=\"1.0\" encoding=\"UTF-8\"?>\n<map version=\"1.0\" orientation=\"orthogonal\" renderorder=\"right-down\" width=\"50\" height=\"50\" tilewidth=\"32\" tileheight=\"32\">\n <tileset firstgid=\"1\" name=\"koudai\" tilewidth=\"32\" tileheight=\"32\">\n  <image source=\"koudai.png\" width=\"256\" height=\"1696\"/>\n  <tile id=\"73\">\n   <properties>\n    <property name=\"type\" value=\"-1\"/>\n   </properties>\n  </tile>\n  <tile id=\"81\">\n   <properties>\n    <property name=\"type\" value=\"-1\"/>\n   </properties>\n  </tile>\n </tileset>\n <layer name=\"l1\" width=\"50\" height=\"50\">\n  <data encoding=\"base64\" compression=\"zlib\">\n   eJzt0rENACAQAkB+LF3l99/D3s5KTa64ngCdpAE2o5JZ93Ngvxfp9z8245TPAAAAAAAAwJ8W0Xd3lQ==\n  </data>\n </layer>\n <layer name=\"l2\" width=\"50\" height=\"50\">\n  <data encoding=\"base64\" compression=\"zlib\">\n   eJzt01EJADAMQ8Hq2+f8i5mJQdNyB3GQVwX/nSW7S0aW7l/rQx/Jun+tD30k6/61PvQBAAAAAAAwwQMg8Hnh\n  </data>\n </layer>\n</map>\n","tmxFolderPath":"resources/tiled","textures":[{"__uuid__":"99773e9b-f6bd-42f9-b096-b14465339913"}]}